lh_text_utils/__init__.py
lh_text_utils/utils.py
lh_text_utils-0.2.0.dist-info/WHEEL
lh_text_utils-0.2.0.dist-info/entry_points.txt
lh_text_utils-0.2.0.dist-info/METADATA
lh_text_utils-0.2.0.dist-info/RECORD
