Metadata-Version: 2.3
Name: lh-text-utils
Version: 0.2.0
Summary: Simple text processing utilities
Keywords: text,utils,processing,learning_hour,lokeshsoni
Author: Lokesh Soni
Author-email: Lokesh Soni <lokesh.soni@cbre.com>
License: MIT
Classifier: Development Status :: 4 - Beta
Classifier: Intended Audience :: Developers
Classifier: License :: OSI Approved :: MIT License
Classifier: Programming Language :: Python :: 3
Classifier: Programming Language :: Python :: 3.11
Classifier: Programming Language :: Python :: 3.12
Requires-Python: >=3.11
